[{"id": 0, "dim": [0.295, 0.192, 0.049], "alias": "Blank", "color": [0.442, 0.738, 0.227]}, {"id": 1, "dim": [0.212, 0.195, 0.099], "alias": "Milano", "color": [0.517, 0.816, 0.715]}, {"id": 2, "dim": [0.305, 0.22, 0.136], "alias": "Amazon box spR6K", "color": [0.711, 0.174, 0.312]}, {"id": 3, "dim": [0.3, 0.27, 0.168], "alias": "Ziploc Box", "color": [0.564, 0.222, 0.914]}, {"id": 4, "dim": [0.2, 0.135, 0.071], "alias": "Green Oatmeal", "color": [0.256, 0.785, 0.647]}, {"id": 5, "dim": [0.2, 0.122, 0.065], "alias": "Blue Oatmeal", "color": [0.167, 0.661, 0.137]}, {"id": 6, "dim": [0.133, 0.133, 0.051], "alias": "Microphone", "color": [0.779, 0.78, 0.648]}, {"id": 7, "dim": [0.175, 0.13, 0.044000000000000004], "alias": "House Again", "color": [0.907, 0.487, 0.031]}, {"id": 8, "dim": [0.07400000000000001, 0.055999999999999994, 0.052000000000000005], "alias": "Lactaid", "color": [0.612, 0.988, 0.105]}, {"id": 9, "dim": [0.212, 0.195, 0.099], "alias": "Milano", "color": [0.652, 0.768, 0.796]}, {"id": 10, "dim": [0.14400000000000002, 0.08, 0.08], "alias": "Blue LED Box", "color": [0.819, 0.451, 0.143]}, {"id": 11, "dim": [0.111, 0.07780000000000001, 0.0687], "alias": "Green Peppermint", "color": [0.573, 0.587, 0.54]}, {"id": 12, "dim": [0.125, 0.113, 0.113], "alias": "Pink Tissue", "color": [0.02, 0.698, 0.372]}, {"id": 13, "dim": [0.19, 0.10099999999999999, 0.08199999999999999], "alias": "P3", "color": [0.395, 0.244, 0.634]}, {"id": 14, "dim": [0.4, 0.20199999999999999, 0.095], "alias": "GPU box", "color": [0.447, 0.638, 0.023]}, {"id": 15, "dim": [0.322, 0.26, 0.20199999999999999], "alias": "Goldberg Amazon", "color": [0.257, 0.904, 0.042]}, {"id": 16, "dim": [0.128, 0.11199999999999999, 0.11199999999999999], "alias": "Blue Lotion", "color": [0.318, 0.49, 0.216]}, {"id": 17, "dim": [0.4, 0.20199999999999999, 0.095], "alias": "GPU box2", "color": [0.674, 0.879, 0.39]}]